{"id":30042,"path":".\\Library\\PackageCache\\com.unity.render-pipelines.core@14.0.12\\Runtime\\Debugging\\Prefabs\\Widgets\\DebugUIVector3.prefab","assetBundleId":-1,"components":[{"type":15,"id":29922,"data":[0.5,0.5,0,0,0,0,590,0,300,0,0,0,0,0,1,1,1,1]},{"type":11,"id":30330,"enabled":1,"class":41,"data":[0,1,1,1,0,0,0,0,0,0,0,0,0]},{"type":11,"id":30332,"enabled":1,"class":42,"data":[0,2]},{"type":5,"id":30334,"enabled":1,"class":43,"data":[15,30046]},{"type":5,"id":30336,"enabled":1,"class":66,"data":[45,30828,62,30818,64,30830,64,30832,64,30834,0.800000011920929,0.800000011920929,0.800000011920929,1,0.25,0.649999976158142,0.800000011920929,1]}],"children":[{"id":30338,"path":".\\Library\\PackageCache\\com.unity.render-pipelines.core@14.0.12\\Runtime\\Debugging\\Prefabs\\Widgets\\DebugUIVector3.prefab","assetBundleId":-1,"components":[{"type":15,"id":30044,"data":[0.5,0.5,0,0,0,0,590,26,0,0,0,0,0,0,1,1,1,1]},{"type":11,"id":30818,"enabled":1,"class":62,"data":[0,null,null,[[[]]],33,30346,33,30836,33,30838,null,null,0,[3,0,null,null,null,null,null,null,null,null],0,[1,1,1,1,0.960784316062927,0.960784316062927,0.960784316062927,1,0.7843137383461,0.7843137383461,0.7843137383461,1,0.960784316062927,0.960784316062927,0.960784316062927,1,0.7843137383461,0.7843137383461,0.7843137383461,0.501960813999176,1,0.100000001490116],[null,null,null,null,null,null,null,null],["Normal","Highlighted","Pressed","Highlighted","Disabled"],1,null,null]}],"children":[{"id":30836,"path":".\\Library\\PackageCache\\com.unity.render-pipelines.core@14.0.12\\Runtime\\Debugging\\Prefabs\\Widgets\\DebugUIVector3.prefab","assetBundleId":-1,"components":[{"type":15,"id":30340,"data":[0,0.5,0,0.5,0,0.5,11,11,0,0,0,0,0,0,1,1,1,1]},{"type":19,"id":31532,"data":[1]},{"type":11,"id":31534,"enabled":1,"class":20,"data":[21,32086,0,0,1,4,1,1,0,0,1,null,null,1,1,1,1,1,1,0,0,0,0]}],"children":[],"data":["Arrow Opened",0,0,0,5]},{"id":30838,"path":".\\Library\\PackageCache\\com.unity.render-pipelines.core@14.0.12\\Runtime\\Debugging\\Prefabs\\Widgets\\DebugUIVector3.prefab","assetBundleId":-1,"components":[{"type":15,"id":30342,"data":[0,0.5,0,0.5,0,0.5,11,11,0,0,0,0,0,0,1,1,1,1]},{"type":19,"id":31528,"data":[1]},{"type":11,"id":31530,"enabled":1,"class":20,"data":[21,32088,0,0,1,4,1,1,0,0,1,null,null,1,1,1,1,1,1,0,0,0,0]}],"children":[],"data":["Arrow Closed",0,1,0,5]},{"id":30840,"path":".\\Library\\PackageCache\\com.unity.render-pipelines.core@14.0.12\\Runtime\\Debugging\\Prefabs\\Widgets\\DebugUIVector3.prefab","assetBundleId":-1,"components":[{"type":15,"id":30344,"data":[0.5,0.5,0,0,1,1,-20,0,10,0,0,0,0,0,1,1,1,1]},{"type":19,"id":31536,"data":[1]},{"type":11,"id":30828,"enabled":1,"class":45,"data":[[49,31350,16,0,0,1,40,3,0,0,0,0,1],"Vector4\n",null,null,1,0.800000011920929,0.800000011920929,0.800000011920929,1,1,0,0,0,0]}],"children":[],"data":["Text",0,1,0,5]}],"data":["Header",0,1,0,5]},{"id":30346,"path":".\\Library\\PackageCache\\com.unity.render-pipelines.core@14.0.12\\Runtime\\Debugging\\Prefabs\\Widgets\\DebugUIVector3.prefab","assetBundleId":-1,"components":[{"type":15,"id":30046,"data":[0.5,0.5,0,1,0,1,590,80,295,-70,0,0,0,0,1,1,1,1]},{"type":11,"id":30820,"enabled":1,"class":41,"data":[1,1,0,1,0,0,0,0,25,0,0,0,0]},{"type":11,"id":30822,"enabled":1,"class":42,"data":[0,1]},{"type":19,"id":30824,"data":[1]},{"type":11,"id":30826,"enabled":1,"class":20,"data":[21,30596,0,0,1,4,1,1,0,0,1,null,null,1,0,0,0,0.250980406999588,1,0,0,0,0]}],"children":[{"id":30842,"path":".\\Library\\PackageCache\\com.unity.render-pipelines.core@14.0.12\\Runtime\\Debugging\\Prefabs\\Widgets\\DebugUIVector3.prefab","assetBundleId":-1,"components":[{"type":15,"id":30348,"data":[0.5,0.5,0,1,0,1,565,26,307.5,-13,0,0,0,0,1,1,1,1]},{"type":5,"id":30830,"enabled":1,"class":64,"data":[45,31538,45,31540,0.800000011920929,0.800000011920929,0.800000011920929,1,0.25,0.649999976158142,0.800000011920929,1]}],"children":[{"id":31560,"path":".\\Library\\PackageCache\\com.unity.render-pipelines.core@14.0.12\\Runtime\\Debugging\\Prefabs\\Widgets\\DebugUIVector3.prefab","assetBundleId":-1,"components":[{"type":15,"id":30844,"data":[0.5,1,0,0,0.5,1,0,0,0,0,0,0,0,0,1,1,1,1]},{"type":19,"id":32122,"data":[1]},{"type":11,"id":31538,"enabled":1,"class":45,"data":[[49,31350,16,0,0,10,40,3,0,0,0,0,1],"X",null,null,1,0.800000011920929,0.800000011920929,0.800000011920929,1,0,0,0,0,0]}],"children":[],"data":["Text",0,1,0,5]},{"id":31556,"path":".\\Library\\PackageCache\\com.unity.render-pipelines.core@14.0.12\\Runtime\\Debugging\\Prefabs\\Widgets\\DebugUIVector3.prefab","assetBundleId":-1,"components":[{"type":15,"id":30846,"data":[0.5,0.5,0.5,0,1,1,0,0,0,0,0,0,0,0,1,1,1,1]},{"type":19,"id":32116,"data":[1]},{"type":11,"id":31540,"enabled":1,"class":45,"data":[[49,31350,16,0,0,1,40,3,0,0,0,0,1],"0",null,null,1,0.800000011920929,0.800000011920929,0.800000011920929,1,0,0,0,0,0]}],"children":[],"data":["Float",0,1,0,5]}],"data":["X",0,1,0,5]},{"id":30848,"path":".\\Library\\PackageCache\\com.unity.render-pipelines.core@14.0.12\\Runtime\\Debugging\\Prefabs\\Widgets\\DebugUIVector3.prefab","assetBundleId":-1,"components":[{"type":15,"id":30350,"data":[0.5,0.5,0,1,0,1,565,26,307.5,-40,0,0,0,0,1,1,1,1]},{"type":5,"id":30832,"enabled":1,"class":64,"data":[45,31546,45,31548,0.800000011920929,0.800000011920929,0.800000011920929,1,0.25,0.649999976158142,0.800000011920929,1]}],"children":[{"id":31552,"path":".\\Library\\PackageCache\\com.unity.render-pipelines.core@14.0.12\\Runtime\\Debugging\\Prefabs\\Widgets\\DebugUIVector3.prefab","assetBundleId":-1,"components":[{"type":15,"id":30850,"data":[0.5,1,0,0,0.5,1,0,0,0,0,0,0,0,0,1,1,1,1]},{"type":19,"id":32120,"data":[1]},{"type":11,"id":31546,"enabled":1,"class":45,"data":[[49,31350,16,0,0,10,40,3,0,0,0,0,1],"Y",null,null,1,0.800000011920929,0.800000011920929,0.800000011920929,1,0,0,0,0,0]}],"children":[],"data":["Text",0,1,0,5]},{"id":31554,"path":".\\Library\\PackageCache\\com.unity.render-pipelines.core@14.0.12\\Runtime\\Debugging\\Prefabs\\Widgets\\DebugUIVector3.prefab","assetBundleId":-1,"components":[{"type":15,"id":30852,"data":[0.5,0.5,0.5,0,1,1,0,0,0,0,0,0,0,0,1,1,1,1]},{"type":19,"id":32118,"data":[1]},{"type":11,"id":31548,"enabled":1,"class":45,"data":[[49,31350,16,0,0,1,40,3,0,0,0,0,1],"0",null,null,1,0.800000011920929,0.800000011920929,0.800000011920929,1,0,0,0,0,0]}],"children":[],"data":["Float",0,1,0,5]}],"data":["Y",0,1,0,5]},{"id":30854,"path":".\\Library\\PackageCache\\com.unity.render-pipelines.core@14.0.12\\Runtime\\Debugging\\Prefabs\\Widgets\\DebugUIVector3.prefab","assetBundleId":-1,"components":[{"type":15,"id":30352,"data":[0.5,0.5,0,1,0,1,565,26,307.5,-67,0,0,0,0,1,1,1,1]},{"type":5,"id":30834,"enabled":1,"class":64,"data":[45,31542,45,31544,0.800000011920929,0.800000011920929,0.800000011920929,1,0.25,0.649999976158142,0.800000011920929,1]}],"children":[{"id":31558,"path":".\\Library\\PackageCache\\com.unity.render-pipelines.core@14.0.12\\Runtime\\Debugging\\Prefabs\\Widgets\\DebugUIVector3.prefab","assetBundleId":-1,"components":[{"type":15,"id":30856,"data":[0.5,1,0,0,0.5,1,0,0,0,0,0,0,0,0,1,1,1,1]},{"type":19,"id":32114,"data":[1]},{"type":11,"id":31542,"enabled":1,"class":45,"data":[[49,31350,16,0,0,10,40,3,0,0,0,0,1],"Z",null,null,1,0.800000011920929,0.800000011920929,0.800000011920929,1,0,0,0,0,0]}],"children":[],"data":["Text",0,1,0,5]},{"id":31550,"path":".\\Library\\PackageCache\\com.unity.render-pipelines.core@14.0.12\\Runtime\\Debugging\\Prefabs\\Widgets\\DebugUIVector3.prefab","assetBundleId":-1,"components":[{"type":15,"id":30858,"data":[0.5,0.5,0.5,0,1,1,0,0,0,0,0,0,0,0,1,1,1,1]},{"type":19,"id":32124,"data":[1]},{"type":11,"id":31544,"enabled":1,"class":45,"data":[[49,31350,16,0,0,1,40,3,0,0,0,0,1],"0",null,null,1,0.800000011920929,0.800000011920929,0.800000011920929,1,0,0,0,0,0]}],"children":[],"data":["Float",0,1,0,5]}],"data":["Z",0,1,0,5]}],"data":["Content",0,0,0,5]}],"data":["DebugUIVector3",0,1,0,0]}